waifuit/main.py
waifuit-0.0.0.dist-info/licenses/LICENSE
waifuit-0.0.0.dist-info/METADATA
waifuit-0.0.0.dist-info/WHEEL
waifuit-0.0.0.dist-info/top_level.txt
waifuit-0.0.0.dist-info/RECORD
