Metadata-Version: 2.4
Name: waifuit
Version: 0.0.0
Summary: A Python wrapper for the waifu.it API.
Author-email: Keksi <hello@keksi.dev>
Requires-Python: >=3.12
License-File: LICENSE
Requires-Dist: httpx>=0.28.1
Dynamic: license-file
